pycarrot/__init__.py
pycarrot/carrot-icon.ico
pycarrot/carrot.py
pycarrot/default-bkg.png
pycarrot/layout.py
pycarrot-0.9.5.data/data/assets/carrot-icon.ico
pycarrot-0.9.5.data/data/assets/default-bkg.png
pycarrot-0.9.5.dist-info/METADATA
pycarrot-0.9.5.dist-info/WHEEL
pycarrot-0.9.5.dist-info/top_level.txt
pycarrot-0.9.5.dist-info/RECORD
