Metadata-Version: 2.1
Name: pycarrot
Version: 0.9.5
Summary: Easy Desktop GUIs
Home-page: UNKNOWN
Author: Jorge Flores
Author-email: <jafp07@gmail.com>
License: UNKNOWN
Keywords: python,first package
Platform: UNKNOWN
Classifier: Development Status :: 3 - Alpha
Classifier: Intended Audience :: Education
Classifier: Programming Language :: Python :: 3
Classifier: Operating System :: MacOS :: MacOS X
Classifier: Operating System :: Microsoft :: Windows
